django_walletpass/__init__.py
django_walletpass/admin.py
django_walletpass/apps.py
django_walletpass/classviews.py
django_walletpass/crypto.py
django_walletpass/files.py
django_walletpass/models.py
django_walletpass/services.py
django_walletpass/settings.py
django_walletpass/signals.py
django_walletpass/storage.py
django_walletpass/urls.py
django_walletpass/certs/AppleWWDRCA.cer
django_walletpass/certs/AppleWWDRCA.pem
django_walletpass/migrations/0001_initial.py
django_walletpass/migrations/0002_auto_20190429_1819.py
django_walletpass/migrations/0003_auto_20190610_1434.py
django_walletpass/migrations/0004_auto_20190611_1306.py
django_walletpass/migrations/0005_auto_20190613_1433.py
django_walletpass/migrations/0006_auto_20190613_1607.py
django_walletpass/migrations/0007_auto_20190613_1807.py
django_walletpass/migrations/0008_alter_pass_data.py
django_walletpass/migrations/0009_auto_20230709_2143.py
django_walletpass/migrations/0010_alter_registration_push_token.py
django_walletpass/migrations/__init__.py
django_walletpass/tests/__init__.py
django_walletpass/tests/main.py
django_walletpass-4.2.1.dist-info/LICENSE
django_walletpass-4.2.1.dist-info/METADATA
django_walletpass-4.2.1.dist-info/WHEEL
django_walletpass-4.2.1.dist-info/top_level.txt
django_walletpass-4.2.1.dist-info/RECORD
