Metadata-Version: 2.1
Name: django-walletpass
Version: 4.2.1
Summary: Django .pkpass builder, server and push notifications
Home-page: http://github.com/develatio/django-walletpass/
Author: Develatio Technologies S.L.
Author-email: contacto@develat.io
License: BSD
Classifier: Intended Audience :: Developers
Classifier: Topic :: Software Development :: Libraries :: Python Modules
Classifier: Development Status :: 5 - Production/Stable
Classifier: Environment :: Web Environment
Classifier: Framework :: Django
Classifier: Intended Audience :: Developers
Classifier: Intended Audience :: System Administrators
Classifier: License :: OSI Approved :: MIT License
Classifier: License :: OSI Approved :: BSD License
Classifier: Operating System :: OS Independent
Classifier: Programming Language :: Python
Classifier: Programming Language :: Python :: 3.10
Classifier: Programming Language :: Python :: 3.11
Classifier: Programming Language :: Python :: 3.12
Classifier: Programming Language :: Python :: Implementation :: CPython
Classifier: Topic :: Software Development :: Internationalization
Classifier: Topic :: Software Development :: Localization
Classifier: Topic :: Internet :: WWW/HTTP
Classifier: Topic :: Internet :: WWW/HTTP :: Dynamic Content
Classifier: Topic :: Software Development :: Libraries :: Application Frameworks
Requires-Python: >=3.10.0
License-File: LICENSE
Requires-Dist: Django >=3.2.9
Requires-Dist: cryptography >=2.4.2
Requires-Dist: aioapns ~=3.3
Requires-Dist: pyopenssl
Requires-Dist: djangorestframework >=3.8
Requires-Dist: python-dateutil
